[1,0,0,[["cc.JsonAsset",["_name","json"],1]],[[0,0,1,3]],[[0,"economy_balance_targets",{"version":1,"global":{"requiredFinalTaskId":"chapter6_candidate_pool","maxWaitTicks":60,"maxEstimatedSeconds":180,"maxActions":211,"maxCollectActions":166,"minFinalCoins":12200,"minFinalBuzz":414},"segments":[{"id":"fast_food_recovery","label":"快餐店救火段","startAfterTaskId":"name_mall","endAtTaskId":"renovate_fast_food","maxWaitTicks":5,"maxEstimatedSeconds":15,"maxActions":10,"maxCollectActions":4,"minEndCoins":40,"minEndBuzz":26},{"id":"fashion_opening","label":"门面店开门段","startAfterTaskId":"renovate_fast_food","endAtTaskId":"unlock_fashion","maxWaitTicks":14,"maxEstimatedSeconds":42,"maxActions":18,"maxCollectActions":12,"minEndCoins":0,"minEndBuzz":46},{"id":"fashion_showcase","label":"门面陈列段","startAfterTaskId":"unlock_fashion","endAtTaskId":"renovate_fashion","maxWaitTicks":6,"maxEstimatedSeconds":18,"maxActions":12,"maxCollectActions":8,"minEndCoins":0,"minEndBuzz":72},{"id":"toy_launch","label":"潮玩店启动段","startAfterTaskId":"renovate_fashion","endAtTaskId":"renovate_toy","maxWaitTicks":8,"maxEstimatedSeconds":24,"maxActions":20,"maxCollectActions":10,"minEndCoins":80,"minEndBuzz":110},{"id":"chapter2_refresh","label":"第二章三店二次爆改段","startAfterTaskId":"renovate_toy","endAtTaskId":"renovate_toy_ch2","maxWaitTicks":10,"maxEstimatedSeconds":30,"maxActions":36,"maxCollectActions":24,"minEndCoins":80,"minEndBuzz":190},{"id":"chapter2_retention","label":"第二章回访与扩张资金段","startAfterTaskId":"renovate_toy_ch2","endAtTaskId":"chapter2_expansion_fund","maxWaitTicks":10,"maxEstimatedSeconds":30,"maxActions":18,"maxCollectActions":12,"minEndCoins":1200,"minEndBuzz":190},{"id":"chapter3_beauty_opening","label":"二层香氛美妆开业段","startAfterTaskId":"chapter2_expansion_fund","endAtTaskId":"beauty_launch_event","maxWaitTicks":9,"maxEstimatedSeconds":27,"maxActions":28,"maxCollectActions":24,"minEndCoins":900,"minEndBuzz":236},{"id":"chapter4_prelude","label":"第四章复购与招商预案段","startAfterTaskId":"beauty_launch_event","endAtTaskId":"chapter4_expansion_plan","maxWaitTicks":13,"maxEstimatedSeconds":39,"maxActions":30,"maxCollectActions":30,"minEndCoins":5600,"minEndBuzz":236},{"id":"chapter4_jewelry_launch","label":"第四章珠宝首饰扩店段","startAfterTaskId":"chapter4_expansion_plan","endAtTaskId":"jewelry_member_event","maxWaitTicks":10,"maxEstimatedSeconds":30,"maxActions":32,"maxCollectActions":28,"minEndCoins":6400,"minEndBuzz":296},{"id":"chapter5_member_center","label":"第五章会员服务中枢段","startAfterTaskId":"jewelry_member_event","endAtTaskId":"member_vip_event","maxWaitTicks":18,"maxEstimatedSeconds":54,"maxActions":36,"maxCollectActions":32,"minEndCoins":4200,"minEndBuzz":340},{"id":"chapter5_member_program","label":"第五章会员机制首场专场段","startAfterTaskId":"member_vip_event","endAtTaskId":"run_member_campaign","maxWaitTicks":8,"maxEstimatedSeconds":24,"maxActions":12,"maxCollectActions":10,"minEndCoins":4500,"minEndBuzz":352},{"id":"chapter5_member_level","label":"第五章会员等级成长段","startAfterTaskId":"run_member_campaign","endAtTaskId":"run_member_level_campaign","maxWaitTicks":4,"maxEstimatedSeconds":12,"maxActions":8,"maxCollectActions":6,"minEndCoins":9500,"minEndBuzz":384},{"id":"chapter5_repurchase_boost","label":"第五章复购周期加成段","startAfterTaskId":"run_member_level_campaign","endAtTaskId":"repurchase_boost_cycle","maxWaitTicks":4,"maxEstimatedSeconds":12,"maxActions":6,"maxCollectActions":3,"minEndCoins":10000,"minEndBuzz":384},{"id":"chapter5_member_loop_plan","label":"第五章会员长期经营入口段","startAfterTaskId":"repurchase_boost_cycle","endAtTaskId":"plan_member_long_term","maxWaitTicks":1,"maxEstimatedSeconds":3,"maxActions":2,"maxCollectActions":0,"minEndCoins":11000,"minEndBuzz":392},{"id":"chapter6_brand_positioning","label":"第六章品牌招商定位入口段","startAfterTaskId":"plan_member_long_term","endAtTaskId":"chapter6_brand_positioning","maxWaitTicks":1,"maxEstimatedSeconds":3,"maxActions":2,"maxCollectActions":0,"minEndCoins":11500,"minEndBuzz":402},{"id":"chapter6_candidate_pool","label":"第六章招商候选池选择段","startAfterTaskId":"chapter6_brand_positioning","endAtTaskId":"chapter6_candidate_pool","maxWaitTicks":1,"maxEstimatedSeconds":3,"maxActions":2,"maxCollectActions":0,"minEndCoins":12200,"minEndBuzz":414}]}]],0,0,[],[],[]]
